pyktx/__init__.py
pyktx/gl_internalformat.py
pyktx/ktx_astc_params.py
pyktx/ktx_basis_params.py
pyktx/ktx_error_code.py
pyktx/ktx_hash_list.py
pyktx/ktx_pack_astc_block_dimension.py
pyktx/ktx_pack_astc_encoder_mode.py
pyktx/ktx_pack_astc_quality_levels.py
pyktx/ktx_pack_uastc_flag_bits.py
pyktx/ktx_supercmp_scheme.py
pyktx/ktx_texture.c
pyktx/ktx_texture.h
pyktx/ktx_texture.py
pyktx/ktx_texture1.c
pyktx/ktx_texture1.h
pyktx/ktx_texture1.py
pyktx/ktx_texture2.c
pyktx/ktx_texture2.h
pyktx/ktx_texture2.py
pyktx/ktx_texture_create_flag_bits.py
pyktx/ktx_texture_create_info.py
pyktx/ktx_texture_create_storage.py
pyktx/ktx_transcode_flag_bits.py
pyktx/ktx_transcode_fmt.py
pyktx/native.pyd
pyktx/vk_format.py
pyktx-4.4.0.dist-info/METADATA
pyktx-4.4.0.dist-info/WHEEL
pyktx-4.4.0.dist-info/top_level.txt
pyktx-4.4.0.dist-info/RECORD
